Samay/Samay.py
Samay/__init__.py
Samay-0.0.4.dist-info/LICENSE
Samay-0.0.4.dist-info/METADATA
Samay-0.0.4.dist-info/WHEEL
Samay-0.0.4.dist-info/top_level.txt
Samay-0.0.4.dist-info/RECORD
